initiate.py
setup.py
django_initiate.egg-info/PKG-INFO
django_initiate.egg-info/SOURCES.txt
django_initiate.egg-info/dependency_links.txt
django_initiate.egg-info/entry_points.txt
django_initiate.egg-info/requires.txt
django_initiate.egg-info/top_level.txt