Metadata-Version: 1.0
Name: django-initiate
Version: 0.1
Summary: Configure .gitignore and local_settings for a django project
Home-page: https://github.com/rmad17/djanjo-initiate
Author: Sourav Basu
Author-email: souravbasu17@gmail.com
License: UNKNOWN
Platform: UNKNOWN
